movie_metadata/__init__.py
movie_metadata/client.py
movie_metadata/constants.py
movie_metadata/exceptions.py
movie_metadata-0.1.0.dist-info/LICENSE
movie_metadata-0.1.0.dist-info/METADATA
movie_metadata-0.1.0.dist-info/WHEEL
movie_metadata-0.1.0.dist-info/top_level.txt
movie_metadata-0.1.0.dist-info/RECORD
