Metadata-Version: 2.1
Name: movie_metadata
Version: 0.1.0
Summary: A Python wrapper for The Movie Database (TMDB) API
Home-page: https://github.com/AhmedOsamaMath/movie-metadata
Author: Ahmed Osama
Author-email: Ahmed Osama <ahmedosamamath@gmail.com>
License: MIT License
Project-URL: Homepage, https://github.com/AhmedOsamaMath/movie-metadata
Project-URL: Documentation, https://github.com/AhmedOsamaMath/movie-metadata/wiki
Project-URL: Repository, https://github.com/AhmedOsamaMath/movie-metadata.git
Project-URL: Bug Tracker, https://github.com/AhmedOsamaMath/movie-metadata/issues
Classifier: Development Status :: 4 - Beta
Classifier: Intended Audience :: Developers
Classifier: License :: OSI Approved :: MIT License
Classifier: Operating System :: OS Independent
Classifier: Programming Language :: Python :: 3
Classifier: Programming Language :: Python :: 3.7
Classifier: Programming Language :: Python :: 3.8
Classifier: Programming Language :: Python :: 3.9
Classifier: Programming Language :: Python :: 3.10
Classifier: Programming Language :: Python :: 3.11
Requires-Python: >=3.7.0
License-File: LICENSE
Requires-Dist: requests>=2.25.0
Requires-Dist: typing-extensions>=4.0.0; python_version < "3.8"
Provides-Extra: dev
Requires-Dist: pytest>=6.0; extra == "dev"
Requires-Dist: pytest-cov>=2.0; extra == "dev"
Requires-Dist: mypy>=0.910; extra == "dev"
Requires-Dist: black>=21.0; extra == "dev"
Requires-Dist: isort>=5.0; extra == "dev"
Requires-Dist: flake8>=3.9; extra == "dev"
Provides-Extra: docs
Requires-Dist: sphinx>=4.0; extra == "docs"
Requires-Dist: sphinx-rtd-theme>=0.5; extra == "docs"
Requires-Dist: myst-parser>=0.15; extra == "docs"
